jinyaml/__init__.py
jinyaml/parser.py
sphinx_jinyaml-0.0.3.dist-info/METADATA
sphinx_jinyaml-0.0.3.dist-info/WHEEL
sphinx_jinyaml-0.0.3.dist-info/top_level.txt
sphinx_jinyaml-0.0.3.dist-info/RECORD
