Metadata-Version: 2.1
Name: sphinx-jinyaml
Version: 0.0.3
Summary: Plugin for sphinx to use Jinja in documents
Home-page: https://github.com/magmax/sphinx-jinyaml
License: MIT
Platform: UNKNOWN
Classifier: Development Status :: 4 - Beta
Classifier: License :: OSI Approved :: MIT License
Classifier: Framework :: Sphinx :: Extension
Requires-Dist: docutils (>=0.11)
Requires-Dist: sphinx (>=1.3.1)
Provides-Extra: markdown
Requires-Dist: commonmark (>=0.8.1) ; extra == 'markdown'
